phjokes/__init__.py
phjokes/main.py
phjokes/jokes/__init__.py
phjokes/jokes/jokes.py
phjokes/utils/__init__.py
phjokes/utils/helpers.py
phjokes-0.0.1.dist-info/LICENCE.md
phjokes-0.0.1.dist-info/METADATA
phjokes-0.0.1.dist-info/WHEEL
phjokes-0.0.1.dist-info/top_level.txt
phjokes-0.0.1.dist-info/RECORD
